<?xml version = '1.0' encoding = 'UTF-8'?>
<Relation class="oracle.dbtools.crest.model.design.logical.Relation" name="Treatment_diagnosis" directorySegmentName="seg_0" id="AFDE8F19-4ACF-2862-E95B-F6445BE51061">
<createdBy>DDinev</createdBy>
<createdTime>2020-10-09 06:36:50 UTC</createdTime>
<ownerDesignName>HostpitalSystem</ownerDesignName>
<engineerTo>
<item key="5F92DC22-2F5E-11B8-AE49-0F5781DDBDAD" value="true"/>
</engineerTo>
<sourcePk>637A8CB4-7EFB-EE81-6BF2-8ADFB3412DD3</sourcePk>
<identifying>false</identifying>
<optionalSource>true</optionalSource>
<optionalTarget>false</optionalTarget>
<sourceCardinality>1</sourceCardinality>
<sourceEntity>CB67F76B-9D8C-22B5-14C0-05F20682DCD3</sourceEntity>
<targetCardinalityString>*</targetCardinalityString>
<targetEntity>5775594D-394E-C4C3-7770-F284441AC7B4</targetEntity>
<transferable>true</transferable>
<deleteRule>NO ACTION</deleteRule>
</Relation>